pytrello2/__init__.py
pytrello2/board.py
pytrello2/card.py
pytrello2/client.py
pytrello2/exceptions.py
pytrello2/list.py
pytrello2/models/__init__.py
pytrello2/models/board.py
pytrello2/models/card.py
pytrello2/models/list.py
pytrello2/models/model.py
pytrello2/utils.py
pytrello2-0.1.0.dist-info/LICENSE
pytrello2-0.1.0.dist-info/METADATA
pytrello2-0.1.0.dist-info/WHEEL
pytrello2-0.1.0.dist-info/RECORD
