Metadata-Version: 2.1
Name: pytrello2
Version: 0.1.0
Summary: Python wrapper for the Trello API
Author: Venu Vardhan Reddy Tekula
Author-email: vt2182@nyu.edu
Requires-Python: >=3.9,<4.0
Classifier: Programming Language :: Python :: 3
Classifier: Programming Language :: Python :: 3.9
Classifier: Programming Language :: Python :: 3.10
Classifier: Programming Language :: Python :: 3.11
Classifier: Programming Language :: Python :: 3.12
Requires-Dist: requests (>=2.31.0,<3.0.0)
